{
	"info": {
		"_postman_id": "5520f1e3-fbcf-472b-8816-28ad07f2de18",
		"name": "caldar-api",
		"description": "Documentation of CaldAR API REST.\r\nHere you'll find all available requests for the CaldAR app API.",
		"schema": "https://schema.getpostman.com/json/collection/v2.1.0/collection.json"
	},
	"item": [
		{
			"name": "Customers - Get all",
			"request": {
				"method": "GET",
				"header": [],
				"url": {
					"raw": "http://localhost:3000/customers",
					"protocol": "http",
					"host": [
						"localhost"
					],
					"port": "3000",
					"path": [
						"customers"
					]
				},
				"description": "Retrieves all customers"
			},
			"response": []
		},
		{
			"name": "Customers - Get one",
			"request": {
				"method": "GET",
				"header": [],
				"url": {
					"raw": "http://localhost:3000/customers/1",
					"protocol": "http",
					"host": [
						"localhost"
					],
					"port": "3000",
					"path": [
						"customers",
						"1"
					]
				},
				"description": "Retrieves the customer with the selected id"
			},
			"response": []
		},
		{
			"name": "Customers - Add",
			"request": {
				"method": "POST",
				"header": [],
				"body": {
					"mode": "raw",
					"raw": "{\r\n    \"id\": 1,\r\n    \"customerType\": \"Construction company\",\r\n    \"email\": \"suppliers@ccr.com\",\r\n    \"buildingsId\": [1,3,7],\r\n    \"fiscalAddress\": \"2201 Mullholand Drive\"\r\n}",
					"options": {
						"raw": {
							"language": "json"
						}
					}
				},
				"url": {
					"raw": "http://localhost:3000/customers",
					"protocol": "http",
					"host": [
						"localhost"
					],
					"port": "3000",
					"path": [
						"customers"
					]
				},
				"description": "Adds a customer. All data fields must be included"
			},
			"response": []
		},
		{
			"name": "Customers - Update one",
			"request": {
				"method": "PUT",
				"header": [],
				"body": {
					"mode": "raw",
					"raw": "{\r\n    \"id\": 1,\r\n    \"customerType\": \"Construction company\",\r\n    \"email\": \"suppliers@ccr.com\",\r\n    \"buildingsId\": [1,3,7],\r\n    \"fiscalAddress\": \"2057 Mullholand Drive\"\r\n}",
					"options": {
						"raw": {
							"language": "json"
						}
					}
				},
				"url": {
					"raw": "http://localhost:3000/customers/1",
					"protocol": "http",
					"host": [
						"localhost"
					],
					"port": "3000",
					"path": [
						"customers",
						"1"
					]
				},
				"description": "Updates one the fields of the customer with the selected id.\r\nAll fields must have data to update the customer."
			},
			"response": []
		},
		{
			"name": "Customers - Delete one",
			"request": {
				"method": "DELETE",
				"header": [],
				"url": {
					"raw": "http://localhost:3000/customers/1",
					"protocol": "http",
					"host": [
						"localhost"
					],
					"port": "3000",
					"path": [
						"customers",
						"1"
					]
				},
				"description": "Deletes customer with specified id."
			},
			"response": []
		}
	],
	"protocolProfileBehavior": {}
}